smol_evm/__init__.py
smol_evm/constants.py
smol_evm/context.py
smol_evm/exceptions.py
smol_evm/memory.py
smol_evm/opcodes.py
smol_evm/runner.py
smol_evm/stack.py
smol_evm/utils.py
smol_evm-0.1.0.dist-info/LICENSE
smol_evm-0.1.0.dist-info/WHEEL
smol_evm-0.1.0.dist-info/entry_points.txt
smol_evm-0.1.0.dist-info/METADATA
smol_evm-0.1.0.dist-info/RECORD
