Metadata-Version: 2.1
Name: smol-evm
Version: 0.1.0
Summary: 👨‍🔬 An extensible Python implementation of the Ethereum yellow paper from scratch.
Home-page: https://github.com/karmacoma-eth/smol-evm
License: MIT
Author: karmacoma
Author-email: karma@coma.lol
Requires-Python: >=3.7,<4.0
Classifier: License :: OSI Approved :: MIT License
Classifier: Programming Language :: Python :: 3
Classifier: Programming Language :: Python :: 3.7
Classifier: Programming Language :: Python :: 3.8
Classifier: Programming Language :: Python :: 3.9
Classifier: Programming Language :: Python :: 3.10
Classifier: Programming Language :: Python :: 3.11
Requires-Dist: click (>=8.1.3,<9.0.0)
Requires-Dist: colorama (>=0.4.6,<0.5.0)
Requires-Dist: eth-utils[pycryptodome] (>=2.0.0,<3.0.0)
Requires-Dist: pycryptodome (>=3.15.0,<4.0.0)
Requires-Dist: tomlkit (>=0.11.5,<0.12.0)
